{
  "b": 209,
  "disableInputWhenNotFocused": true,
  "mangledName": "Game",
  "name": "Game",
  "oglFOV": 90,
  "oglZFar": 500,
  "oglZNear": 1,
  "r": 209,
  "standardSortMethod": true,
  "stopSoundsOnStartup": true,
  "title": "",
  "v": 209,
  "uiSettings": {
    "grid": false,
    "gridB": 255,
    "gridG": 180,
    "gridHeight": 32,
    "gridOffsetX": 0,
    "gridOffsetY": 0,
    "gridR": 158,
    "gridType": "rectangular",
    "gridWidth": 32,
    "snap": true,
    "windowMask": false,
    "zoomFactor": 0.7667999999999991
  },
  "objectsGroups": [],
  "variables": [],
  "instances": [],
  "objects": [],
  "events": [
    {
      "disabled": false,
      "folded": false,
      "type": "BuiltinCommonInstructions::Comment",
      "color": {
        "b": 109,
        "g": 230,
        "r": 255,
        "textB": 0,
        "textG": 0,
        "textR": 0
      },
      "comment": "This should be the ONLY event on this events sheet. If you are trying to add events for the game scene, click on the button below to open \"GameEvents\", rather than adding them here.",
      "comment2": ""
    },
    {
      "disabled": false,
      "folded": false,
      "type": "BuiltinCommonInstructions::Link",
      "include": {
        "includeConfig": 0
      },
      "target": "GameEvents"
    }
  ],
  "layers": [
    {
      "ambientLightColorB": 0,
      "ambientLightColorG": 0,
      "ambientLightColorR": 0,
      "followBaseLayerCamera": false,
      "isLightingLayer": false,
      "name": "",
      "visibility": true,
      "cameras": [
        {
          "defaultSize": true,
          "defaultViewport": true,
          "height": 0,
          "viewportBottom": 1,
          "viewportLeft": 0,
          "viewportRight": 1,
          "viewportTop": 0,
          "width": 0
        }
      ],
      "effects": []
    }
  ],
  "behaviorsSharedData": []
}